[
  {
    "title": "Red Mountain Resort",
    "type": "lodging",
    "star_rating": false,
    "image": "/sites/default/files/styles/thumbnail/public/places/main-photos/red_mountain_resort.jpg?itok=WVMUohZx",
    "indoor": null,
    "node_url": "/lodging/ivins-ut/red-mountain-resort",
    "price": null,
    "radioactivity": "0.0000",
    "location": "Ivins, UT",
    "cuisine": [],
    "lodging_type": "",
    "difficulty": null,
    "category": "",
    "hike_type": "",
    "id": ""
  },
  {
    "title": "Sheraton Park City",
    "type": "lodging",
    "star_rating": false,
    "image": "/sites/default/files/styles/thumbnail/public/places/main-photos/sheraton_park_city.jpg?itok=cFKp_Zwv",
    "indoor": null,
    "node_url": "/lodging/park-city-ut/sheraton-park-city",
    "price": null,
    "radioactivity": "0.0000",
    "location": "Park City, UT",
    "cuisine": [],
    "lodging_type": "",
    "difficulty": null,
    "category": "",
    "hike_type": "",
    "id": ""
  },
  {
    "title": "Skyline Mountain Resort",
    "type": "lodging",
    "star_rating": false,
    "image": "/sites/default/files/styles/thumbnail/public/places/main-photos/skyline_mountain_resort.jpg?itok=ky33ZaeF",
    "indoor": null,
    "node_url": "/lodging/fairview-ut/skyline-mountain-resort",
    "price": null,
    "radioactivity": "0.0000",
    "location": "Fairview, UT",
    "cuisine": [],
    "lodging_type": "",
    "difficulty": null,
    "category": "",
    "hike_type": "",
    "id": ""
  },
  {
    "title": "The Lodge at The Mountain Village",
    "type": "lodging",
    "star_rating": false,
    "image": "/sites/default/files/styles/thumbnail/public/places/main-photos/the_lodge_at_the_mountain_village.jpg?itok=WYY67A2o",
    "indoor": null,
    "node_url": "/lodging/park-city-ut/lodge-mountain-village",
    "price": null,
    "radioactivity": "0.0000",
    "location": "Park City, UT",
    "cuisine": [],
    "lodging_type": "",
    "difficulty": null,
    "category": "",
    "hike_type": "",
    "id": ""
  },
  {
    "title": "Treasure Mountain Inn",
    "type": "lodging",
    "star_rating": false,
    "image": "/sites/default/files/styles/thumbnail/public/places/main-photos/treasure_mountain_inn.jpg?itok=unOwwlrg",
    "indoor": null,
    "node_url": "/lodging/park-city-ut/treasure-mountain-inn",
    "price": null,
    "radioactivity": "0.0000",
    "location": "Park City, UT",
    "cuisine": [],
    "lodging_type": "",
    "difficulty": null,
    "category": "",
    "hike_type": "",
    "id": ""
  },
  {
    "title": "AC Hotel Salt Lake City Downtown",
    "type": "lodging",
    "star_rating": false,
    "image": "/sites/default/files/styles/thumbnail/public/places/main-photos/ac_hotel_salt_lake_city_downtown.jpg?itok=5rVkdSdt",
    "indoor": null,
    "node_url": "/lodging/salt-lake-city-ut/ac-hotel-salt-lake-city-downtown",
    "price": null,
    "radioactivity": "0.0000",
    "location": "Salt Lake City, UT",
    "cuisine": [],
    "lodging_type": "",
    "difficulty": null,
    "category": "",
    "hike_type": "",
    "id": ""
  },
  {
    "title": "University Guest House and Conference Center",
    "type": "lodging",
    "star_rating": false,
    "image": "/sites/default/files/styles/thumbnail/public/places/main-photos/university_guest_house_and_conference_center.jpg?itok=hTaTU2-0",
    "indoor": null,
    "node_url": "/lodging/salt-lake-city-ut/university-guest-house-and-conference-center",
    "price": null,
    "radioactivity": "0.0000",
    "location": "Salt Lake City, UT",
    "cuisine": [],
    "lodging_type": "",
    "difficulty": null,
    "category": "",
    "hike_type": "",
    "id": ""
  },
  {
    "title": "Broken Spur Inn and Steakhouse",
    "type": "lodging",
    "star_rating": false,
    "image": "/sites/default/files/styles/thumbnail/public/places/main-photos/broken_spur_inn_and_steakhouse.jpg?itok=GK8hwp7Q",
    "indoor": null,
    "node_url": "/lodging/torrey-ut/broken-spur-inn-and-steakhouse",
    "price": null,
    "radioactivity": "0.0000",
    "location": "Torrey, UT",
    "cuisine": [],
    "lodging_type": "",
    "difficulty": null,
    "category": "",
    "hike_type": "",
    "id": ""
  },
  {
    "title": "Zermatt Resort",
    "type": "lodging",
    "star_rating": false,
    "image": "/sites/default/files/styles/thumbnail/public/places/main-photos/zermatt_resort.jpg?itok=EBSuX6uD",
    "indoor": null,
    "node_url": "/lodging/midway-ut/zermatt-resort",
    "price": null,
    "radioactivity": "0.0000",
    "location": "Midway, UT",
    "cuisine": [],
    "lodging_type": "",
    "difficulty": null,
    "category": "",
    "hike_type": "",
    "id": ""
  },
  {
    "title": "Cable Mountain Lodge",
    "type": "lodging",
    "star_rating": false,
    "image": "/sites/default/files/styles/thumbnail/public/places/main-photos/cable_mountain_lodge.jpg?itok=Il8QHfnE",
    "indoor": null,
    "node_url": "/lodging/springdale-ut/cable-mountain-lodge",
    "price": null,
    "radioactivity": "0.0000",
    "location": "Springdale, UT",
    "cuisine": [],
    "lodging_type": "",
    "difficulty": null,
    "category": "",
    "hike_type": "",
    "id": ""
  },
  {
    "title": "Zion Ponderosa Ranch Resort",
    "type": "lodging",
    "star_rating": false,
    "image": "/sites/default/files/styles/thumbnail/public/places/main-photos/zion_ponderosa_ranch_resort.jpg?itok=kid72QjN",
    "indoor": null,
    "node_url": "/lodging/orderville-ut/zion-ponderosa-ranch-resort",
    "price": null,
    "radioactivity": "0.0000",
    "location": "Orderville, UT",
    "cuisine": [],
    "lodging_type": "",
    "difficulty": null,
    "category": "",
    "hike_type": "",
    "id": ""
  },
  {
    "title": "Diamond Campground",
    "type": "lodging",
    "star_rating": false,
    "image": "/sites/default/files/styles/thumbnail/public/places/main-photos/diamond_campground.jpg?itok=0Q7ZKRl6",
    "indoor": null,
    "node_url": "/lodging/springville-ut/diamond-campground",
    "price": null,
    "radioactivity": "0.0000",
    "location": "Springville, UT",
    "cuisine": [],
    "lodging_type": "",
    "difficulty": null,
    "category": "",
    "hike_type": "",
    "id": ""
  },
  {
    "title": "Access RV Rental",
    "type": "lodging",
    "star_rating": false,
    "image": "/sites/default/files/styles/thumbnail/public/places/main-photos/access_rv_rental.jpg?itok=l6UUAZ6f",
    "indoor": null,
    "node_url": "/lodging/north-salt-lake-ut/access-rv-rental",
    "price": null,
    "radioactivity": "0.0000",
    "location": "North Salt Lake, UT",
    "cuisine": [],
    "lodging_type": "",
    "difficulty": null,
    "category": "",
    "hike_type": "",
    "id": ""
  },
  {
    "title": "El Rey Inn and Suites",
    "type": "lodging",
    "star_rating": false,
    "image": "/sites/default/files/styles/thumbnail/public/places/main-photos/el_rey_inn_and_suites.jpg?itok=eD_8mUVS",
    "indoor": null,
    "node_url": "/lodging/cedar-city-ut/el-rey-inn-and-suites",
    "price": null,
    "radioactivity": "0.0000",
    "location": "Cedar City, UT",
    "cuisine": [],
    "lodging_type": "",
    "difficulty": null,
    "category": "",
    "hike_type": "",
    "id": ""
  },
  {
    "title": "Dinosaur Inn and Suites",
    "type": "lodging",
    "star_rating": false,
    "image": "/sites/default/files/styles/thumbnail/public/places/main-photos/dinosaur_inn_and_suites.jpg?itok=Xf1IeIhZ",
    "indoor": null,
    "node_url": "/lodging/vernal-ut/dinosaur-inn-and-suites",
    "price": null,
    "radioactivity": "0.0000",
    "location": "Vernal, UT",
    "cuisine": [],
    "lodging_type": "",
    "difficulty": null,
    "category": "",
    "hike_type": "",
    "id": ""
  },
  {
    "title": "Epic RV Park and Marina",
    "type": "lodging",
    "star_rating": false,
    "image": "/sites/default/files/styles/thumbnail/public/places/main-photos/epic_rv_park_and_marina.jpg?itok=W5x4HNgQ",
    "indoor": null,
    "node_url": "/lodging/garden-city-ut/epic-rv-park-and-marina",
    "price": null,
    "radioactivity": "0.0000",
    "location": "Garden City, UT",
    "cuisine": [],
    "lodging_type": "",
    "difficulty": null,
    "category": "",
    "hike_type": "",
    "id": ""
  },
  {
    "title": "South Fork Campgrounds",
    "type": "lodging",
    "star_rating": false,
    "image": "/sites/default/files/styles/thumbnail/public/places/main-photos/south_fork_campgrounds.jpg?itok=9QuMlP3I",
    "indoor": null,
    "node_url": "/lodging/huntsville-ut/south-fork-campgrounds",
    "price": null,
    "radioactivity": "0.0000",
    "location": "Huntsville, UT",
    "cuisine": [],
    "lodging_type": "",
    "difficulty": null,
    "category": "",
    "hike_type": "",
    "id": ""
  },
  {
    "title": "Escalante Outfitters",
    "type": "lodging",
    "star_rating": false,
    "image": "/sites/default/files/styles/thumbnail/public/places/main-photos/escalante_outfitters.jpg?itok=IuULvQwN",
    "indoor": null,
    "node_url": "/lodging/escalante-ut/escalante-outfitters",
    "price": null,
    "radioactivity": "0.0000",
    "location": "Escalante, UT",
    "cuisine": [],
    "lodging_type": "",
    "difficulty": null,
    "category": "",
    "hike_type": "",
    "id": ""
  },
  {
    "title": "The Grand America Hotel",
    "type": "lodging",
    "star_rating": false,
    "image": "/sites/default/files/styles/thumbnail/public/places/main-photos/the_grand_america_hotel.jpg?itok=M1QqmHTl",
    "indoor": null,
    "node_url": "/lodging/salt-lake-city-ut/grand-america-hotel",
    "price": null,
    "radioactivity": "0.0000",
    "location": "Salt Lake City, UT",
    "cuisine": [],
    "lodging_type": "",
    "difficulty": null,
    "category": "",
    "hike_type": "",
    "id": ""
  },
  {
    "title": "Homestead Resort",
    "type": "lodging",
    "star_rating": false,
    "image": "/sites/default/files/styles/thumbnail/public/places/main-photos/homestead_resort.jpg?itok=_eioXVsB",
    "indoor": null,
    "node_url": "/lodging/midway-ut/homestead-resort",
    "price": null,
    "radioactivity": "0.0000",
    "location": "Midway, UT",
    "cuisine": [],
    "lodging_type": "",
    "difficulty": null,
    "category": "",
    "hike_type": "",
    "id": ""
  },
  {
    "title": "Willard Bay Cabins",
    "type": "lodging",
    "star_rating": false,
    "image": "/sites/default/files/styles/thumbnail/public/places/main-photos/willard_bay_cabins.jpg?itok=vKA_XZwx",
    "indoor": null,
    "node_url": "/lodging/willard-ut/willard-bay-cabins",
    "price": null,
    "radioactivity": "0.0000",
    "location": "Willard, UT",
    "cuisine": [],
    "lodging_type": "",
    "difficulty": null,
    "category": "",
    "hike_type": "",
    "id": ""
  },
  {
    "title": "Hoovers River Resort",
    "type": "lodging",
    "star_rating": false,
    "image": "/sites/default/files/styles/thumbnail/public/places/main-photos/hoovers_river_resort.jpg?itok=9oAe_jQL",
    "indoor": null,
    "node_url": "/lodging/marysvale-ut/hoovers-river-resort",
    "price": null,
    "radioactivity": "0.0000",
    "location": "Marysvale, UT",
    "cuisine": [],
    "lodging_type": "",
    "difficulty": null,
    "category": "",
    "hike_type": "",
    "id": ""
  },
  {
    "title": "Herm's Inn",
    "type": "lodging",
    "star_rating": false,
    "image": "/sites/default/files/styles/thumbnail/public/places/main-photos/herms_inn.jpg?itok=qW7RKJZ1",
    "indoor": null,
    "node_url": "/lodging/cache-county-ut/herms-inn",
    "price": null,
    "radioactivity": "0.0000",
    "location": "Cache County, UT",
    "cuisine": [],
    "lodging_type": "",
    "difficulty": null,
    "category": "",
    "hike_type": "",
    "id": ""
  },
  {
    "title": "My Place Hotel",
    "type": "lodging",
    "star_rating": false,
    "image": "/sites/default/files/styles/thumbnail/public/places/main-photos/my_place_hotel.jpg?itok=1pis7JRd",
    "indoor": null,
    "node_url": "/lodging/st-george-ut/my-place-hotel",
    "price": null,
    "radioactivity": "0.0000",
    "location": "St. George, UT",
    "cuisine": [],
    "lodging_type": "",
    "difficulty": null,
    "category": "",
    "hike_type": "",
    "id": ""
  },
  {
    "title": "Hyatt Place Farmington Station",
    "type": "lodging",
    "star_rating": false,
    "image": "/sites/default/files/styles/thumbnail/public/places/main-photos/hyatt_place_farmington_station.jpg?itok=xVoJ0Ju2",
    "indoor": null,
    "node_url": "/lodging/farmington-ut/hyatt-place-farmington-station",
    "price": null,
    "radioactivity": "0.0000",
    "location": "Farmington, UT",
    "cuisine": [],
    "lodging_type": "",
    "difficulty": null,
    "category": "",
    "hike_type": "",
    "id": ""
  },
  {
    "title": "Nunns Park",
    "type": "lodging",
    "star_rating": false,
    "image": "/sites/default/files/styles/thumbnail/public/places/main-photos/nunns_park.jpg?itok=AePvOxy8",
    "indoor": null,
    "node_url": "/lodging/provo-ut/nunns-park",
    "price": null,
    "radioactivity": "0.0000",
    "location": "Provo, UT",
    "cuisine": [],
    "lodging_type": "",
    "difficulty": null,
    "category": "",
    "hike_type": "",
    "id": ""
  },
  {
    "title": "Microtel Inn and Suites by Wyndham",
    "type": "lodging",
    "star_rating": false,
    "image": "/sites/default/files/styles/thumbnail/public/places/main-photos/microtel_inn_and_suites_by_wyndham.jpg?itok=2UKtdqR0",
    "indoor": null,
    "node_url": "/lodging/naples-ut/microtel-inn-and-suites-wyndham",
    "price": null,
    "radioactivity": "0.0000",
    "location": "Naples, UT",
    "cuisine": [],
    "lodging_type": "",
    "difficulty": null,
    "category": "",
    "hike_type": "",
    "id": ""
  }
]
